lime_etl/__init__.py
lime_etl/adapter/__init__.py
lime_etl/adapter/admin_orm.py
lime_etl/adapter/sqlalchemy_admin_session.py
lime_etl/adapter/sqlalchemy_admin_unit_of_work.py
lime_etl/adapter/sqlalchemy_batch_log_repository.py
lime_etl/adapter/sqlalchemy_batch_logger.py
lime_etl/adapter/sqlalchemy_batch_repository.py
lime_etl/adapter/sqlalchemy_job_log_repository.py
lime_etl/adapter/sqlalchemy_job_logger.py
lime_etl/adapter/sqlalchemy_job_repository.py
lime_etl/domain/__init__.py
lime_etl/domain/admin_unit_of_work.py
lime_etl/domain/batch_delta.py
lime_etl/domain/batch_log_entry.py
lime_etl/domain/batch_log_repository.py
lime_etl/domain/batch_logger.py
lime_etl/domain/batch_repository.py
lime_etl/domain/batch_spec.py
lime_etl/domain/batch_status.py
lime_etl/domain/cfg.py
lime_etl/domain/exceptions.py
lime_etl/domain/job_dependency_errors.py
lime_etl/domain/job_log_entry.py
lime_etl/domain/job_log_repository.py
lime_etl/domain/job_logger.py
lime_etl/domain/job_repository.py
lime_etl/domain/job_result.py
lime_etl/domain/job_spec.py
lime_etl/domain/job_status.py
lime_etl/domain/job_test_result.py
lime_etl/domain/timestamp_adapter.py
lime_etl/domain/value_objects.py
lime_etl/py.typed
lime_etl/service/__init__.py
lime_etl/service/admin/__init__.py
lime_etl/service/admin/admin_batch.py
lime_etl/service/admin/delete_old_logs.py
lime_etl/service/batch_runner.py
lime_etl-0.1.30.dist-info/license.txt
lime_etl-0.1.30.dist-info/WHEEL
lime_etl-0.1.30.dist-info/METADATA
lime_etl-0.1.30.dist-info/RECORD
