Metadata-Version: 2.1
Name: lime-etl
Version: 0.1.30
Summary: Simple ETL job runner
License: MIT
Author: Mark Stefanovic
Requires-Python: >=3.8,<4.0
Classifier: License :: OSI Approved :: MIT License
Classifier: Programming Language :: Python :: 3
Classifier: Programming Language :: Python :: 3.8
Classifier: Programming Language :: Python :: 3.9
Requires-Dist: lime-uow (>=0.1.46)
Requires-Dist: sqlalchemy (>=1.3.19,<2.0)
